README.rst
setup.py
src/slowdown/__init__.py
src/slowdown/__main__.py
src/slowdown/captcha.py
src/slowdown/cgi.py
src/slowdown/exceptions.py
src/slowdown/fs.py
src/slowdown/gvars.py
src/slowdown/http.py
src/slowdown/inotify.py
src/slowdown/logging.py
src/slowdown/lrucache.py
src/slowdown/mapfs.py
src/slowdown/sysutil.py
src/slowdown/threadpool.py
src/slowdown/token.py
src/slowdown/urlencode.py
src/slowdown.egg-info/PKG-INFO
src/slowdown.egg-info/SOURCES.txt
src/slowdown.egg-info/dependency_links.txt
src/slowdown.egg-info/entry_points.txt
src/slowdown.egg-info/requires.txt
src/slowdown.egg-info/top_level.txt